MANIFEST.in
Makefile
README.md
README.rst
requirements-test.txt
requirements.txt
requirements_utils.py
setup.cfg
setup.py
jsjinja/__init__.py
jsjinja/compiler.py
jsjinja/ext.py
jsjinja/utils.py
jsjinja.egg-info/PKG-INFO
jsjinja.egg-info/SOURCES.txt
jsjinja.egg-info/dependency_links.txt
jsjinja.egg-info/entry_points.txt
jsjinja.egg-info/requires.txt
jsjinja.egg-info/top_level.txt
jsjinja/lib/jinja2.runtime.js
jsjinja/lib/jinja2.runtime.min.js
jsjinja/tests/__init__.py
jsjinja/tests/__init__.pyc
jsjinja/tests/test_templates.py
jsjinja/tests/test_templates.pyc
jsjinja/tests/templates/block.tmpl
jsjinja/tests/templates/condexpr.tmpl
jsjinja/tests/templates/context.tmpl
jsjinja/tests/templates/eval.tmpl
jsjinja/tests/templates/extends.tmpl
jsjinja/tests/templates/filters.tmpl
jsjinja/tests/templates/for.tmpl
jsjinja/tests/templates/globals.tmpl
jsjinja/tests/templates/if.tmpl
jsjinja/tests/templates/import.tmpl
jsjinja/tests/templates/include.tmpl
jsjinja/tests/templates/macro.tmpl
jsjinja/tests/templates/set.tmpl
jsjinja/tests/templates/tests.tmpl
jsjinja/tests/templates/unicode.tmpl
jsjinja/tests/templates/partials/include.tmpl
jsjinja/tests/templates/partials/layout.tmpl