Metadata-Version: 1.1
Name: jsjinja
Version: 0.3.1
Summary: Jinja2 to Javascript compiler
Home-page: https://github.com/syrusakbary/jsjinja
Author: Syrus Akbary
Author-email: me@syrusakbary.com
License: UNKNOWN
Download-URL: git@github.com:syrusakbary/jsjinja.git
Keywords: jinja2 javascript converter coffeescript
Platform: any
Classifier: Development Status :: 2 - Pre-Alpha
Classifier: Environment :: Console
Classifier: Intended Audience :: Developers
Classifier: License :: OSI Approved :: BSD License
Classifier: Operating System :: OS Independent
Classifier: Programming Language :: Python :: 2.6
Classifier: Programming Language :: Python :: 2.7
Classifier: Topic :: Scientific/Engineering
